AUTHORS.rst
CHANGES.rst
LICENSE
MANIFEST.in
README.rst
setup.cfg
setup.py
Attest_latest.egg-info/PKG-INFO
Attest_latest.egg-info/SOURCES.txt
Attest_latest.egg-info/dependency_links.txt
Attest_latest.egg-info/entry_points.txt
Attest_latest.egg-info/not-zip-safe
Attest_latest.egg-info/requires.txt
Attest_latest.egg-info/top_level.txt
attest/__init__.py
attest/__main__.py
attest/ast.py
attest/codegen.py
attest/collectors.py
attest/contexts.py
attest/deprecated.py
attest/hook.py
attest/pygments.py
attest/reporters.py
attest/run.py
attest/statistics.py
attest/utils.py
attest/tests/__init__.py
attest/tests/_meta.py
attest/tests/asserts.py
attest/tests/classy.py
attest/tests/collectors.py
attest/tests/contexts.py
attest/tests/hook.py
attest/tests/reporters.py
attest/tests/utils.py
attest/tests/dummy/__init__.py
attest/tests/dummy/foo.py
docs/changes.rst
docs/glossary.rst
docs/index.rst
docs/install.rst
docs/meta.rst
docs/quickstart.rst
docs/api/collectors.rst
docs/api/contexts.rst
docs/api/deprecated.rst
docs/api/hook.rst
docs/api/reporters.rst