Metadata-Version: 1.1
Name: Attest-latest
Version: 0.6.1dev-20130603
Summary: Modern, Pythonic unit testing.
Home-page: https://github.com/dag/attest
Author: Dag Odenhall
Author-email: dag.odenhall@gmail.com
License: Simplified BSD
Platform: UNKNOWN
Classifier: Development Status :: 4 - Beta
Classifier: Intended Audience :: Developers
Classifier: License :: OSI Approved :: BSD License
Classifier: Programming Language :: Python
Classifier: Programming Language :: Python :: 2.5
Classifier: Programming Language :: Python :: 2.6
Classifier: Programming Language :: Python :: 2.7
Classifier: Programming Language :: Python :: 3.1
Classifier: Programming Language :: Python :: 3.2
Classifier: Topic :: Software Development :: Testing
